recipe_lib/__init__.py
recipe_lib/recipes.py
recipe_lib/utils.py
recipe_lib-0.2.0.dist-info/licenses/LICENSE
recipe_lib-0.2.0.dist-info/METADATA
recipe_lib-0.2.0.dist-info/WHEEL
recipe_lib-0.2.0.dist-info/top_level.txt
recipe_lib-0.2.0.dist-info/RECORD
